rofi.py
python_rofi-1.0.1.dist-info/DESCRIPTION.rst
python_rofi-1.0.1.dist-info/METADATA
python_rofi-1.0.1.dist-info/RECORD
python_rofi-1.0.1.dist-info/WHEEL
python_rofi-1.0.1.dist-info/metadata.json
python_rofi-1.0.1.dist-info/top_level.txt
python_rofi-1.0.1.dist-info/zip-safe
